pyscriber/__init__.py
pyscriber-0.0.0.dist-info/METADATA
pyscriber-0.0.0.dist-info/WHEEL
pyscriber-0.0.0.dist-info/top_level.txt
pyscriber-0.0.0.dist-info/RECORD
